easyknn/__init__.py
easyknn/item_store.py
easyknn/knn.py
easyknn-0.5.0.dist-info/METADATA
easyknn-0.5.0.dist-info/WHEEL
easyknn-0.5.0.dist-info/RECORD
